MANIFEST.in
README.rst
setup.cfg
setup.py
pyctrl/__init__.py
pyctrl/client.py
pyctrl/packet.py
pyctrl/server.py
pyctrl/sim.py
pyctrl/timer.py
pyctrl.egg-info/PKG-INFO
pyctrl.egg-info/SOURCES.txt
pyctrl.egg-info/dependency_links.txt
pyctrl.egg-info/top_level.txt
pyctrl/bbb/__init__.py
pyctrl/bbb/analog.py
pyctrl/bbb/cosmos.py
pyctrl/bbb/encoder.py
pyctrl/bbb/eqep.py
pyctrl/bbb/gpio.py
pyctrl/bbb/imu.py
pyctrl/bbb/motor.py
pyctrl/bbb/mpu6050.py
pyctrl/bbb/robut.py
pyctrl/bbb/strawson.py
pyctrl/bbb/util.py
pyctrl/bbb/pycomms/__init__.py
pyctrl/bbb/pycomms/mpu6050.py
pyctrl/block/__init__.py
pyctrl/block/clock.py
pyctrl/block/logic.py
pyctrl/block/nl.py
pyctrl/block/random.py
pyctrl/block/system.py
pyctrl/rc/__init__.py
pyctrl/rc/encoder.py
pyctrl/rc/gpio.py
pyctrl/rc/imu.py
pyctrl/rc/mip.py
pyctrl/rc/motor.py
pyctrl/rc/mpu9250.py
pyctrl/system/__init__.py
pyctrl/system/ode.py
pyctrl/system/ss.py
pyctrl/system/tf.py
scripts/pyctrl_start_server
scripts/pyctrl_stop_server
test/__init__.py
test/test_block.py
test/test_block_system.py
test/test_clock.py
test/test_ctrl.py
test/test_logic.py
test/test_nl.py
test/test_packet.py
test/test_random.py
test/test_rc.py
test/test_simulation.py
test/test_system.py