Metadata-Version: 1.2
Name: pyctrl
Version: 0.3.1
Summary: Python Suite for Systems and Control
Home-page: https://github.com/mcdeoliveira/pyctrl
Author: Mauricio C. de Oliveira
Author-email: mauricio@ucsd.edu
License: Apache-2.0
Download-URL: https://github.com/mcdeoliveira/pyctrl/archive/0.3.tar.gz
Keywords: feedback control systems beaglebone black Robotics Cape
Platform: UNKNOWN
Classifier: Development Status :: 3 - Alpha
Classifier: Intended Audience :: Other Audience
Classifier: Topic :: Scientific/Engineering
Classifier: License :: OSI Approved :: Apache Software License
Classifier: Programming Language :: Python :: 3.4
Requires-Python: >=3.4
